pythonmoneyspace
