Metadata-Version: 1.1
Name: python-moneyspace
Version: 0.0.2
Summary: Python class to connect with moneyspace.net payment gateway
Home-page: https://github.com/joncombe/python-moneyspace
Author: Jon Combe
Author-email: jon@salebox.io
License: BSD licence, see LICENCE file
Platform: UNKNOWN
Classifier: Development Status :: 3 - Alpha
Classifier: Environment :: Web Environment
Classifier: Intended Audience :: Developers
Classifier: License :: OSI Approved :: BSD License
Classifier: Natural Language :: English
Classifier: Operating System :: OS Independent
Classifier: Programming Language :: Python
